growler_jade-0.0.1-py3.5-nspkg.pth
growler_ext/JadeRenderer/__init__.py
growler_ext/jade_renderer/__init__.py
growler_jade/__init__.py
growler_jade/__meta__.py
growler_jade/jade_renderer.py
growler_jade-0.0.1.dist-info/DESCRIPTION.rst
growler_jade-0.0.1.dist-info/METADATA
growler_jade-0.0.1.dist-info/RECORD
growler_jade-0.0.1.dist-info/WHEEL
growler_jade-0.0.1.dist-info/metadata.json
growler_jade-0.0.1.dist-info/namespace_packages.txt
growler_jade-0.0.1.dist-info/top_level.txt
