Metadata-Version: 2.0
Name: growler-jade
Version: 0.0.1
Summary: An extension providing a jade renderer for growler applications
Home-page: https://github.com/pyGrowler/growler-jade
Author: Andrew Kubera
Author-email: andrewkubera@gmail.com
License: BSD
Download-URL: https://github.com/pygrowler/growler-jade/archive/v0.0.1.tar.gz
Platform: all
Classifier: Development Status :: 1 - Planning
Classifier: Environment :: Web Environment
Classifier: Operating System :: OS Independent
Classifier: License :: OSI Approved :: BSD License
Classifier: Programming Language :: Python
Classifier: Programming Language :: Python :: 3
Classifier: Programming Language :: Python :: 3.5
Classifier: Topic :: Internet :: WWW/HTTP
Classifier: Natural Language :: English
Requires-Dist: mako
Requires-Dist: pyjade
